hogwarts_logger/__init__.py
hogwarts_logger/core/__init__.py
hogwarts_logger/core/logger.py
hogwarts_logger/core/pycharm_formatter.py
hogwarts_logger/core/time_interval_filter.py
hogwarts_logger-1.0.0.dist-info/METADATA
hogwarts_logger-1.0.0.dist-info/WHEEL
hogwarts_logger-1.0.0.dist-info/top_level.txt
hogwarts_logger-1.0.0.dist-info/RECORD
