Metadata-Version: 2.4
Name: hogwarts-logger
Version: 1.0.0
Summary: 用于测试框架的日志封装
Author: 霍格沃兹测试开发学社 https://ceshiren.com
Project-URL: Homepage, https://ceshiren.com
Requires-Python: >=3.9
Requires-Dist: pyyaml
Requires-Dist: pytest
Requires-Dist: coverage
Requires-Dist: pydantic
